rccc/__init__.py
rccc-0.3.dist-info/LICENCE.txt
rccc-0.3.dist-info/METADATA
rccc-0.3.dist-info/WHEEL
rccc-0.3.dist-info/top_level.txt
rccc-0.3.dist-info/RECORD
