Metadata-Version: 2.1
Name: rccc
Version: 0.3
Summary: Taking color code of resistance wire and giving the value of resistance in ohms
Author: VASU JAIN
Author-email: vasu.jain20022002@gmail.com
Classifier: Programming Language :: Python :: 3
Classifier: License :: OSI Approved :: MIT License
Classifier: Operating System :: OS Independent
License-File: LICENCE.txt
